lc_checkpoint/__init__.py
lc_checkpoint/main.py
lc_checkpoint-0.5.2.dist-info/LICENSE
lc_checkpoint-0.5.2.dist-info/METADATA
lc_checkpoint-0.5.2.dist-info/WHEEL
lc_checkpoint-0.5.2.dist-info/top_level.txt
lc_checkpoint-0.5.2.dist-info/RECORD
