Metadata-Version: 2.1
Name: lc-checkpoint
Version: 0.5.2
Summary: A package for compressing PyTorch model checkpoints using the LC-Checkpoint method
Home-page: https://pypi.org/project/lc-checkpoint/
Author: Dedy Van Hauten
Author-email: dedy.van@ui.ac.id
Classifier: Programming Language :: Python :: 3
Classifier: License :: OSI Approved :: MIT License
Classifier: Operating System :: OS Independent
Requires-Python: >=3.8
License-File: LICENSE
